{
  "code": 0,
  "msg": "",
  "count": 1000,
  "data": [
    {
      "id": "1",
      "studentNumber": "201726170011",
      "name": "张三",
      "sex": "男",
      "date": "2017-09-01",
      "nativePlace": "大同市浑源县",
      "qq":"3255604242",
      "contactWay": "15303652139",
      "whetherEmployment": "是"
    },
    {
      "id": "2",
      "studentNumber": "201726170011",
      "name": "张三",
      "sex": "男",
      "date": "2017-09-01",
      "nativePlace": "大同市浑源县",
      "qq":"3255604242",
      "contactWay": "15303652139",
      "whetherEmployment": "是"
    },
    {
      "id": "3",
      "studentNumber": "201726170011",
      "name": "张三",
      "sex": "男",
      "date": "2017-09-01",
      "nativePlace": "大同市浑源县",
      "qq":"3255604242",
      "contactWay": "15303652139",
      "whetherEmployment": "是"
    },
    {
      "id": "4",
      "studentNumber": "201726170011",
      "name": "张三",
      "sex": "男",
      "date": "2017-09-01",
      "nativePlace": "大同市浑源县",
      "qq":"3255604242",
      "contactWay": "15303652139",
      "whetherEmployment": "是"
    },
    {
      "id": "5",
      "studentNumber": "201726170011",
      "name": "张三",
      "sex": "男",
      "date": "2017-09-01",
      "nativePlace": "大同市浑源县",
      "qq":"3255604242",
      "contactWay": "15303652139",
      "whetherEmployment": "是"
    },
    {
      "id": "6",
      "studentNumber": "201726170011",
      "name": "张三",
      "sex": "男",
      "date": "2017-09-01",
      "nativePlace": "大同市浑源县",
      "qq":"3255604242",
      "contactWay": "15303652139",
      "whetherEmployment": "是"
    }
  ]
}